{
  "correct": 75142,
  "incorrect": 8897,
  "marks": 84002,
  "not_marked": 37,
  "not_ntbg": 74919,
  "not_ntbg_correct": 67054,
  "not_ntbg_incorrect": 7865,
  "not_ntbg_plural": 21780,
  "not_ntbg_singular": 51914,
  "nouns": 69143,
  "nouns_not_ntbg": 60235,
  "nouns_not_ntbg_correct": 53898,
  "nouns_not_ntbg_incorrect": 6337,
  "nouns_ntbg": 8908,
  "nouns_ntbg_correct": 7952,
  "nouns_ntbg_incorrect": 956,
  "ntbg": 9120,
  "ntbg_correct": 8088,
  "ntbg_incorrect": 1032,
  "ntbg_plural": 7994,
  "ntbg_singular": 1072,
  "num_undetermined": 1279,
  "plural": 29774,
  "plural_not_ntbg_correct": 20344,
  "plural_not_ntbg_incorrect": 1436,
  "plural_ntbg_correct": 7205,
  "plural_ntbg_incorrect": 789,
  "pronouns": 14896,
  "pronouns_not_ntbg": 14684,
  "pronouns_not_ntbg_correct": 13156,
  "pronouns_not_ntbg_incorrect": 1528,
  "pronouns_ntbg": 212,
  "pronouns_ntbg_correct": 136,
  "pronouns_ntbg_incorrect": 76,
  "singular": 52986,
  "singular_not_ntbg_correct": 45504,
  "singular_not_ntbg_incorrect": 6410,
  "singular_ntbg_correct": 846,
  "singular_ntbg_incorrect": 226
}